{
  "paths": {
    "app": "app",

    "jquery-ui": "jqueryui/jquery-ui.custom.min",
    "jquerycaret": "jquerytag/jquery.caret.min",
    "jquerytageditor": "jquerytag/jquery.tag-editor.min",
    "d3": "d3/d3.min",
    "calendar-heatmap": "d3/calendar-heatmap",
    "jstree": "jstree3/dist/jstree.min",
    "moment": "moment/moment.min",
    "qtip": "qtip2/jquery.qtip.min",
    "domReady": "requirejs/domReady",
    "toastr": "toastr/toastr.min",
    "vue": "vue/vue.min",

    "changelog": "kajona/changelog",
    "downloadIndicator": "kajona/downloadIndicator",
    "folderview": "kajona/folderview",
    "forms": "kajona/forms",
    "instantSave": "kajona/instantSave",
    "loader": "kajona/loader",
    "messaging": "kajona/messaging",
    "moduleNavigation": "kajona/moduleNavigation",
    "permissions": "kajona/permissions",
    "router": "kajona/router",
    "systemTask": "kajona/systemTask",
    "tree": "kajona/tree"
  },
  "shim": {
    "jquery-ui" : {
      "deps": ["jquery"]
    },
    "jquerycaret" : {
      "deps": ["jquery"]
    },
    "jquerytageditor" : {
      "deps": ["jquery", "jquerycaret"]
    }
  }
}
